{"State.a75bc7ba-29ba-47d5-a486-debb29e7e47d": {"name": "California", "id": "a75bc7ba-29ba-47d5-a486-debb29e7e47d", "created_at": "2024-02-19T11:25:25.420803", "updated_at": "2024-02-19T11:25:25.420813", "__class__": "State"}, "State.1661277a-9270-437b-a82d-e912d610e99b": {"name": "Arizona", "id": "1661277a-9270-437b-a82d-e912d610e99b", "created_at": "2024-02-19T11:25:25.421520", "updated_at": "2024-02-19T11:25:25.421527", "__class__": "State"}, "Place.066cdcae-6969-42a7-a3e9-ac3651dbb979": {"city_id": "0001", "user_id": "0001", "name": "My little house", "number_rooms": 4, "number_bathrooms": 2, "max_guest": 10, "price_by_night": 300, "latitude": 37.773972, "longitude": -122.431297, "id": "066cdcae-6969-42a7-a3e9-ac3651dbb979", "created_at": "2024-02-19T11:25:25.422620", "updated_at": "2024-02-19T11:25:25.422623", "__class__": "Place"}, "State.bb4095d2-b70a-4b5a-a97d-a64375fc54c6": {"name": "California", "id": "bb4095d2-b70a-4b5a-a97d-a64375fc54c6", "created_at": "2024-02-19T11:29:55.017767", "updated_at": "2024-02-19T11:29:55.017775", "__class__": "State"}, "State.ff4c16d7-f854-4fed-aed1-7b157408a34f": {"name": "Arizona", "id": "ff4c16d7-f854-4fed-aed1-7b157408a34f", "created_at": "2024-02-19T11:29:55.019418", "updated_at": "2024-02-19T11:29:55.019424", "__class__": "State"}, "Place.efd781c3-2787-435c-a40b-733cf34bf227": {"city_id": "0001", "user_id": "0001", "name": "My little house", "number_rooms": 4, "number_bathrooms": 2, "max_guest": 10, "price_by_night": 300, "latitude": 37.773972, "longitude": -122.431297, "id": "efd781c3-2787-435c-a40b-733cf34bf227", "created_at": "2024-02-19T11:29:55.021066", "updated_at": "2024-02-19T11:29:55.021069", "__class__": "Place"}, "State.f9149d8f-2154-47ec-aae0-8d8b8f531092": {"name": "California", "id": "f9149d8f-2154-47ec-aae0-8d8b8f531092", "created_at": "2024-02-19T11:33:49.228120", "updated_at": "2024-02-19T11:33:49.228132", "__class__": "State"}, "State.5860ce04-b43f-407f-85ba-2bedf6743704": {"name": "Arizona", "id": "5860ce04-b43f-407f-85ba-2bedf6743704", "created_at": "2024-02-19T11:33:49.230059", "updated_at": "2024-02-19T11:33:49.230066", "__class__": "State"}, "Place.0bc29d49-1515-4ff0-bcf6-687095cc3d64": {"city_id": "0001", "user_id": "0001", "name": "My little house", "number_rooms": 4, "number_bathrooms": 2, "max_guest": 10, "price_by_night": 300, "latitude": 37.773972, "longitude": -122.431297, "id": "0bc29d49-1515-4ff0-bcf6-687095cc3d64", "created_at": "2024-02-19T11:33:49.232588", "updated_at": "2024-02-19T11:33:49.232594", "__class__": "Place"}}